mu_inference/__init__.py
mu_inference/cli.py
mu_inference/core/__init__.py
mu_inference/core/cache.py
mu_inference/core/config.py
mu_inference/core/mu.py
mu_inference/core/scheduler.py
mu_inference/models/__init__.py
mu_inference/models/base.py
mu_inference/models/deep.py
mu_inference/models/layers.py
mu_inference/models/llama.py
mu_inference/models/loader.py
mu_inference/models/registry.py
mu_inference/serving/__init__.py
mu_inference/serving/engine.py
mu_inference/serving/server.py
mu_inference/serving/worker.py
mu_inference/utils/__init__.py
mu_inference/utils/sampling.py
mu_inference/utils/tokenizer.py
mu_inference-0.2.10.dist-info/METADATA
mu_inference-0.2.10.dist-info/WHEEL
mu_inference-0.2.10.dist-info/entry_points.txt
mu_inference-0.2.10.dist-info/top_level.txt
mu_inference-0.2.10.dist-info/RECORD
