Metadata-Version: 2.4
Name: mu-inference
Version: 0.2.10
Summary: Mu-Guided High-Performance LLM Inference Engine
Author-email: INL Research <research@inl.ai>
License: Apache-2.0
Project-URL: Homepage, https://github.com/Complexity-ML/mu-inference
Project-URL: Documentation, https://github.com/Complexity-ML/mu-inference#readme
Project-URL: Repository, https://github.com/Complexity-ML/mu-inference
Keywords: llm,inference,transformer,moe,mu-dynamics,inl,complexity-deep,continuous-batching,batch-inference
Classifier: Development Status :: 4 - Beta
Classifier: Intended Audience :: Developers
Classifier: Intended Audience :: Science/Research
Classifier: License :: OSI Approved :: Apache Software License
Classifier: Programming Language :: Python :: 3
Classifier: Programming Language :: Python :: 3.10
Classifier: Programming Language :: Python :: 3.11
Classifier: Programming Language :: Python :: 3.12
Classifier: Topic :: Scientific/Engineering :: Artificial Intelligence
Requires-Python: >=3.10
Requires-Dist: torch>=2.0.0
Requires-Dist: transformers>=4.30.0
Requires-Dist: safetensors>=0.3.0
Requires-Dist: huggingface-hub>=0.16.0
Requires-Dist: fastapi>=0.100.0
Requires-Dist: uvicorn[standard]>=0.22.0
Requires-Dist: pydantic>=2.0.0
Requires-Dist: aiohttp>=3.8.0
Requires-Dist: numpy>=1.24.0
Provides-Extra: dev
Requires-Dist: pytest>=7.0.0; extra == "dev"
Requires-Dist: pytest-asyncio>=0.21.0; extra == "dev"
Requires-Dist: black>=23.0.0; extra == "dev"
Requires-Dist: ruff>=0.0.270; extra == "dev"
